cratonml/__init__.py
cratonml/calculate/__init__.py
cratonml/calculate/Calculate.py
cratonml/calculate/Classification.py
cratonml/calculate/Clustering.py
cratonml/calculate/curve_utils.py
cratonml/calculate/DimensionReduction.py
cratonml/calculate/metrics.py
cratonml/calculate/PostProcessing.py
cratonml/calculate/Prepare.py
cratonml/calculate/Regression.py
cratonml/calculate/Statistics.py
cratonml/data/__init__.py
cratonml/data/Cube.py
cratonml/data/Grid.py
cratonml/data/Outline.py
cratonml/data/Well.py
cratonml/exceptions/__init__.py
cratonml/exceptions/DataExceptions.py
cratonml/exceptions/WellExceptions.py
cratonml-0.1.1.37.dist-info/METADATA
cratonml-0.1.1.37.dist-info/WHEEL
cratonml-0.1.1.37.dist-info/RECORD
