Metadata-Version: 2.4
Name: cratonml
Version: 0.1.1.37
Summary: Python application for W-Seis
Author: KamashevAM
Author-email: kamashev41@gmail.com
Requires-Python: >=3.11,<3.13
Classifier: Programming Language :: Python :: 3
Classifier: Programming Language :: Python :: 3.11
Classifier: Programming Language :: Python :: 3.12
Requires-Dist: cratonapi (>=0.1.0.22,<0.2.0.0)
Requires-Dist: imbalanced-learn (>=0.12.4,<0.13.0)
Requires-Dist: nose2 (>=0.15.1,<0.16.0)
Requires-Dist: numpy (>=1.26.4,<2.0.0)
Requires-Dist: scikit-learn (==1.6)
Requires-Dist: scipy (==1.15.3)
Requires-Dist: typing-extensions (>=4.13.2,<5.0.0)
